che/__init__.py
che/binding.py
che/main.py
che/utils.py
che/intercept/__init__.py
che/intercept/cache.py
che/intercept/chain.py
che/intercept/conversation.py
che/intercept/interceptor.py
che/intercept/markdown.py
che/intercept/request.py
che/intercept/vote.py
copilothistoryexporter-1.2.6.dist-info/LICENCE
copilothistoryexporter-1.2.6.dist-info/METADATA
copilothistoryexporter-1.2.6.dist-info/WHEEL
copilothistoryexporter-1.2.6.dist-info/entry_points.txt
copilothistoryexporter-1.2.6.dist-info/top_level.txt
copilothistoryexporter-1.2.6.dist-info/RECORD
