Metadata-Version: 2.1
Name: copilothistoryexporter
Version: 1.2.6
Summary: Copilot History Exporter
Author-email: enciyo <enciyomk61@gmail.com>
Project-URL: Homepage, https://github.com/enciyo/gh-copilot-history-export
Project-URL: Source, https://github.com/enciyo/gh-copilot-history-export
Project-URL: Documentation, https://github.com/enciyo/gh-copilot-history-export
Requires-Python: >=3.11
License-File: LICENCE
Requires-Dist: click ~=8.1.7
Requires-Dist: mitmproxy ~=10.3.0
